LICENSE
vault_client/__init__.py
vault_client/client.py
simple_vault_client-0.0.1.dist-info/LICENSE
simple_vault_client-0.0.1.dist-info/WHEEL
simple_vault_client-0.0.1.dist-info/METADATA
simple_vault_client-0.0.1.dist-info/RECORD
