Metadata-Version: 2.1
Name: simple-vault-client
Version: 0.0.1
Summary: Dead simple HashiCorp Vault consumer client
Home-page: https://github.com/mbrancato/vault-client
License: Apache-2.0
Keywords: hashicorp,vault,client
Author: Mike Brancato
Author-email: mike@mikebrancato.com
Requires-Python: >=3.5.0,<4
Classifier: License :: OSI Approved :: Apache Software License
Classifier: Programming Language :: Python :: 3
Classifier: Programming Language :: Python :: 3.5
Classifier: Programming Language :: Python :: 3.6
Classifier: Programming Language :: Python :: 3.7
Classifier: Programming Language :: Python :: 3.8
Classifier: Programming Language :: Python :: 3.9
Requires-Dist: requests (>=2.20.0)
Project-URL: Repository, https://github.com/mbrancato/vault-client
